{
  "id": "api.form.read",
  "params": {
    "resmsgid": "154b200d-8602-4188-adda-883df413eec9",
    "msgid": "c1b0b165-5819-4ba5-ac91-7c3944c51bf2",
    "status": "successful"
  },
  "responseCode": "OK",
  "result": {
    "form": {
      "type": "ImgConfig",
      "subtype": "global",
      "action": "read",
      "component": "*",
      "framework": "*",
      "data": {
        "action": "list",
        "fields": [
          {
            "identifier": "nulp-domain_board_solidwastemanagement",
            "code": "solidwastemanagement",
            "translations": null,
            "name": "Solid Waste Management",
            "description": "Solid Waste Management",
            "index": 1,
            "category": "board",
            "status": "Live",
            "image": "/swm.png"
          },
          {
            "identifier": "nulp-domain_board_environmentandclimate",
            "code": "environmentandclimate",
            "translations": null,
            "name": "Environment and Climate",
            "description": "Environment and Climate",
            "index": 2,
            "category": "board",
            "status": "Live",
            "image": "/uran.png"
          },
          {
            "identifier": "nulp-domain_board_wash",
            "code": "wash",
            "translations": null,
            "name": "WASH - Water, Sanitation and Hygiene",
            "description": "WASH - Water, Sanitation and Hygiene",
            "index": 3,
            "category": "board",
            "status": "Live",
            "image": "/water.png"
          },
          {
            "identifier": "nulp-domain_board_urbanplanningandhousing",
            "code": "urbanplanningandhousing",
            "translations": null,
            "name": "Urban Planning and Housing",
            "description": "Urban Planning and Housing",
            "index": 4,
            "category": "board",
            "status": "Live",
            "image": "/building.png"
          },
          {
            "identifier": "nulp-domain_board_transportandmobility",
            "code": "transportandmobility",
            "translations": null,
            "name": "Transport and Mobility",
            "description": "Transport and Mobility",
            "index": 5,
            "category": "board",
            "status": "Live",
            "image": "/savage.png"
          },
          {
            "identifier": "nulp-domain_board_socialaspects",
            "code": "socialaspects",
            "translations": null,
            "name": "Social Aspects",
            "description": "Social Aspects",
            "index": 6,
            "category": "board",
            "status": "Live",
            "image": "/social.png"
          },
          {
            "identifier": "nulp-domain_board_municipalfinance",
            "code": "municipalfinance",
            "translations": null,
            "name": "Municipal Finance",
            "description": "Municipal Finance",
            "index": 7,
            "category": "board",
            "status": "Live",
            "image": "/gov.png"
          },
          {
            "identifier": "nulp-domain_board_generaladministration",
            "code": "generaladministration",
            "translations": null,
            "name": "General Administration",
            "description": "General Administration",
            "index": 8,
            "category": "board",
            "status": "Live",
            "image": "/health.png"
          },
          {
            "identifier": "nulp-domain_board_governanceandurbanmanagement",
            "code": "governanceandurbanmanagement",
            "translations": null,
            "name": "Governance and Urban Management",
            "description": "Governance and Urban Management",
            "index": 9,
            "category": "board",
            "status": "Live",
            "image": "/admin.png"
          },
          {
            "identifier": "nulp-domain_board_miscellaneousothers",
            "code": "miscellaneousothers",
            "translations": null,
            "name": "Miscellaneous/ Others",
            "description": "Miscellaneous/ Others",
            "index": 10,
            "category": "board",
            "status": "Live",
            "image": "/mobility.png"
          }
        ],
        "templateName": "domainImgConfig"
      },

      "rootOrgId": "*"
    }
  },
  "ts": "2024-04-04T10:53:06.023Z",
  "ver": "1.0"
}
